pyLIA.py
pyLIA-0.2.dist-info/LICENSE.txt
pyLIA-0.2.dist-info/METADATA
pyLIA-0.2.dist-info/WHEEL
pyLIA-0.2.dist-info/top_level.txt
pyLIA-0.2.dist-info/RECORD
