Metadata-Version: 2.1
Name: pyLIA
Version: 0.2
Summary: Module for Lock-In Analysis
Home-page: https://github.com/LolloCappo/pyLIA
Author: Lorenzo Capponi
Author-email: lorenzocapponi@outlook.it
License: UNKNOWN
Platform: UNKNOWN
Requires-Dist: numpy (>=1.16.5)
